AUTHORS
Changelog
LICENSE
MANIFEST.in
README.rst
setup.cfg
setup.py
tox.ini
deux/__init__.py
deux/abstract_models.py
deux/app_settings.py
deux/constants.py
deux/exceptions.py
deux/models.py
deux/notifications.py
deux/serializers.py
deux/services.py
deux/strings.py
deux/urls.py
deux/validators.py
deux/views.py
deux/authtoken/__init__.py
deux/authtoken/serializers.py
deux/authtoken/urls.py
deux/authtoken/views.py
deux/authtoken/tests/__init__.py
deux/authtoken/tests/test_serializers.py
deux/authtoken/tests/test_views.py
deux/migrations/0001_initial.py
deux/migrations/__init__.py
deux/oauth2/__init__.py
deux/oauth2/backends.py
deux/oauth2/exceptions.py
deux/oauth2/urls.py
deux/oauth2/validators.py
deux/oauth2/views.py
deux/oauth2/tests/__init__.py
deux/oauth2/tests/test_authentication.py
deux/tests/__init__.py
deux/tests/test_base.py
deux/tests/test_models.py
deux/tests/test_notifications.py
deux/tests/test_services.py
deux/tests/test_validators.py
deux/tests/test_views.py
deux_q5.egg-info/PKG-INFO
deux_q5.egg-info/SOURCES.txt
deux_q5.egg-info/dependency_links.txt
deux_q5.egg-info/not-zip-safe
deux_q5.egg-info/requires.txt
deux_q5.egg-info/top_level.txt
docs/Makefile
docs/_dummy_key_images.rst
docs/changelog.rst
docs/conf.py
docs/contributing.rst
docs/copyright.rst
docs/index.rst
docs/introduction.rst
docs/make.bat
docs/images/deux_banner.png
docs/images/deux_banner_text.png
docs/images/favicon.ico
docs/images/logo.png
docs/images/state_diagram.png
docs/includes/installation.txt
docs/includes/introduction.txt
docs/includes/resources.txt
docs/includes/start.txt
docs/reference/deux.abstract_models.rst
docs/reference/deux.authtoken.rst
docs/reference/deux.authtoken.serializers.rst
docs/reference/deux.authtoken.views.rst
docs/reference/deux.constants.rst
docs/reference/deux.exceptions.rst
docs/reference/deux.models.rst
docs/reference/deux.notifications.rst
docs/reference/deux.oauth2.backends.rst
docs/reference/deux.oauth2.exceptions.rst
docs/reference/deux.oauth2.rst
docs/reference/deux.oauth2.validators.rst
docs/reference/deux.oauth2.views.rst
docs/reference/deux.rst
docs/reference/deux.serializers.rst
docs/reference/deux.services.rst
