Metadata-Version: 1.1
Name: deux-q5
Version: 1.3.0
Summary: Multifactor Authentication for Django Rest Framework
Home-page: https://github.com/robinhood/deux
Author: Robinhood Markets
Author-email: opensource@robinhood.com
License: BSD
Platform: any
Classifier: Development Status :: 4 - Beta
Classifier: License :: OSI Approved :: BSD License
Classifier: Programming Language :: Python
Classifier: Programming Language :: Python :: 2
Classifier: Programming Language :: Python :: 2.7
Classifier: Programming Language :: Python :: 3
Classifier: Programming Language :: Python :: 3.4
Classifier: Programming Language :: Python :: 3.5
Classifier: Programming Language :: Python :: Implementation :: CPython
Classifier: Programming Language :: Python :: Implementation :: PyPy
Classifier: Framework :: Django
Classifier: Framework :: Django :: 1.9
Classifier: Framework :: Django :: 1.10
Classifier: Operating System :: OS Independent
